odoo/addons/event_registration_mass_mailing/README.rst
odoo/addons/event_registration_mass_mailing/__init__.py
odoo/addons/event_registration_mass_mailing/__manifest__.py
odoo/addons/event_registration_mass_mailing/i18n/es.po
odoo/addons/event_registration_mass_mailing/i18n/event_registration_mass_mailing.pot
odoo/addons/event_registration_mass_mailing/i18n/fr.po
odoo/addons/event_registration_mass_mailing/i18n/it.po
odoo/addons/event_registration_mass_mailing/readme/CONTRIBUTORS.rst
odoo/addons/event_registration_mass_mailing/readme/DESCRIPTION.rst
odoo/addons/event_registration_mass_mailing/readme/USAGE.rst
odoo/addons/event_registration_mass_mailing/security/ir.model.access.csv
odoo/addons/event_registration_mass_mailing/static/description/icon.png
odoo/addons/event_registration_mass_mailing/static/description/index.html
odoo/addons/event_registration_mass_mailing/tests/__init__.py
odoo/addons/event_registration_mass_mailing/tests/test_event_registration_mail_list_wizard.py
odoo/addons/event_registration_mass_mailing/views/event_registration.xml
odoo/addons/event_registration_mass_mailing/wizard/__init__.py
odoo/addons/event_registration_mass_mailing/wizard/event_registration_mail_list_wizard.py
odoo/addons/event_registration_mass_mailing/wizard/event_registration_mail_list_wizard.xml
odoo14_addon_event_registration_mass_mailing-14.0.1.0.1.dev8.dist-info/METADATA
odoo14_addon_event_registration_mass_mailing-14.0.1.0.1.dev8.dist-info/WHEEL
odoo14_addon_event_registration_mass_mailing-14.0.1.0.1.dev8.dist-info/top_level.txt
odoo14_addon_event_registration_mass_mailing-14.0.1.0.1.dev8.dist-info/RECORD
